cityloc/__init__.py
cityloc/db.py
cityloc/lookup.py
cityloc/resources/cities.db
cityloc-0.1.0.dist-info/LICENSE
cityloc-0.1.0.dist-info/METADATA
cityloc-0.1.0.dist-info/WHEEL
cityloc-0.1.0.dist-info/top_level.txt
cityloc-0.1.0.dist-info/RECORD
