Metadata-Version: 2.1
Name: cityloc
Version: 0.1.0
Summary: Look up world city coordinates and country codes
Home-page: https://github.com/sveinbjornt/cityloc
Author: Sveinbjorn Thordarson
Author-email: sveinbjorn@sveinbjorn.org
License: BSD
Platform: UNKNOWN
Classifier: License :: OSI Approved :: BSD License
Classifier: Operating System :: OS Independent
Classifier: Development Status :: 5 - Production/Stable
Classifier: Intended Audience :: Developers
Classifier: Programming Language :: Python
Classifier: Programming Language :: Python :: 3
Classifier: Programming Language :: Python :: 3.4
Classifier: Programming Language :: Python :: 3.5
Classifier: Programming Language :: Python :: 3.6
Classifier: Programming Language :: Python :: 3.7
Classifier: Topic :: Software Development :: Libraries :: Python Modules
Classifier: Topic :: Utilities
